datarobotx/__init__.py
datarobotx/_version.py
datarobotx/py.typed
datarobotx/client/__init__.py
datarobotx/client/credentials.py
datarobotx/client/datasets.py
datarobotx/client/deployments.py
datarobotx/client/prediction_servers.py
datarobotx/client/projects.py
datarobotx/client/registered_models.py
datarobotx/client/status.py
datarobotx/common/__init__.py
datarobotx/common/client.py
datarobotx/common/config.py
datarobotx/common/configurator.py
datarobotx/common/dr_config.py
datarobotx/common/logging.py
datarobotx/common/transformations.py
datarobotx/common/ts_helpers.py
datarobotx/common/types.py
datarobotx/common/utils.py
datarobotx/llm/__init__.py
datarobotx/llm/utils.py
datarobotx/llm/chains/__init__.py
datarobotx/llm/chains/data_dict.py
datarobotx/llm/chains/enrich.py
datarobotx/llm/chains/guard.py
datarobotx/llm/pydantic_v1/__init__.py
datarobotx/mlflow/__init__.py
datarobotx/mlflow/drx_mlflow.py
datarobotx/models/__init__.py
datarobotx/models/autoanomaly.py
datarobotx/models/autocluster.py
datarobotx/models/automl.py
datarobotx/models/autopilot.py
datarobotx/models/autots.py
datarobotx/models/colreduce.py
datarobotx/models/deploy.py
datarobotx/models/deployment.py
datarobotx/models/evaluation.py
datarobotx/models/featurediscovery.py
datarobotx/models/intraproject.py
datarobotx/models/model.py
datarobotx/models/selfdiscovery.py
datarobotx/models/share.py
datarobotx/models/sparkingest.py
datarobotx/openblueprints/__init__.py
datarobotx/openblueprints/blueprint_converter.py
datarobotx/openblueprints/blueprint_mappings.py
datarobotx/openblueprints/blueprint_string_converter.py
datarobotx/openblueprints/boosted_enet.py
datarobotx/openblueprints/enums.py
datarobotx/openblueprints/feature_extraction.py
datarobotx/openblueprints/feature_selectors.py
datarobotx/openblueprints/mapping_object.py
datarobotx/openblueprints/single_column_selector.py
datarobotx/openblueprints/stacked_ngram.py
datarobotx/openblueprints/task_mappings.yaml
datarobotx/viz/__init__.py
datarobotx-0.2.0.dist-info/LICENSE
datarobotx-0.2.0.dist-info/METADATA
datarobotx-0.2.0.dist-info/WHEEL
datarobotx-0.2.0.dist-info/top_level.txt
datarobotx-0.2.0.dist-info/RECORD
