Metadata-Version: 2.1
Name: datarobotx
Version: 0.2.0
Summary: DataRobotX is a collection of DataRobot extensions
Home-page: https://drx.datarobot.com/
Author: DataRobot
Author-email: datarobotx@datarobot.com
License: DataRobot Tool and Utility Agreement
Classifier: Development Status :: 3 - Alpha
Classifier: Intended Audience :: Developers
Classifier: Intended Audience :: Science/Research
Classifier: Topic :: Scientific/Engineering :: Artificial Intelligence
Classifier: License :: Other/Proprietary License
Classifier: Operating System :: OS Independent
Classifier: Programming Language :: Python :: 3
Classifier: Programming Language :: Python :: 3 :: Only
Classifier: Programming Language :: Python :: 3.8
Classifier: Programming Language :: Python :: 3.9
Classifier: Programming Language :: Python :: 3.10
Classifier: Programming Language :: Python :: 3.11
Requires-Python: >=3.8
License-File: LICENSE
Requires-Dist: aiohttp
Requires-Dist: altair<5.0.0
Requires-Dist: cloudpickle==2.2.1
Requires-Dist: datarobot>=3.2.0
Requires-Dist: IPython
Requires-Dist: ipywidgets
Requires-Dist: names-generator
Requires-Dist: pandas
Requires-Dist: PyYaml
Requires-Dist: setuptools
Requires-Dist: tenacity
Requires-Dist: termcolor
Requires-Dist: tqdm
Requires-Dist: urllib3<2.0.0
Provides-Extra: deploy
Requires-Dist: scikit-learn; extra == "deploy"
Provides-Extra: dev
Requires-Dist: black==22.8.0; extra == "dev"
Requires-Dist: black[jupyter]==22.8.0; extra == "dev"
Requires-Dist: isort==5.10.1; extra == "dev"
Requires-Dist: pytest; extra == "dev"
Requires-Dist: pytest-sphinx; extra == "dev"
Requires-Dist: pytest-asyncio; extra == "dev"
Requires-Dist: vcrpy<4.4.0; extra == "dev"
Requires-Dist: pytest-cov; extra == "dev"
Requires-Dist: twine>=1.11.0; extra == "dev"
Requires-Dist: setuptools; extra == "dev"
Requires-Dist: wheel; extra == "dev"
Requires-Dist: packaging; extra == "dev"
Requires-Dist: aiohttp; extra == "dev"
Requires-Dist: cmdkit==2.6.1; extra == "dev"
Requires-Dist: datarobot>=3.2.0; extra == "dev"
Requires-Dist: urllib3<2.0.0; extra == "dev"
Requires-Dist: ipython; extra == "dev"
Requires-Dist: ipywidgets; extra == "dev"
Requires-Dist: names-generator; extra == "dev"
Requires-Dist: pandas; extra == "dev"
Requires-Dist: PyYaml; extra == "dev"
Requires-Dist: tenacity; extra == "dev"
Requires-Dist: termcolor; extra == "dev"
Requires-Dist: tqdm; extra == "dev"
Requires-Dist: altair<5.0.0; extra == "dev"
Requires-Dist: category-encoders; extra == "dev"
Requires-Dist: xgboost; extra == "dev"
Requires-Dist: lightgbm; extra == "dev"
Requires-Dist: vecstack; extra == "dev"
Requires-Dist: scikit-learn; extra == "dev"
Requires-Dist: gplearn; extra == "dev"
Requires-Dist: cloudpickle==2.2.1; extra == "dev"
Requires-Dist: transformers; extra == "dev"
Requires-Dist: torch>=1.6.0; extra == "dev"
Requires-Dist: pyspark==3.4.1; extra == "dev"
Requires-Dist: mlflow; extra == "dev"
Requires-Dist: pydantic<3; extra == "dev"
Requires-Dist: langchain-openai==0.1.8; extra == "dev"
Requires-Dist: openai<1.0.0; extra == "dev"
Requires-Dist: datarobot-mlops>10.0.0; extra == "dev"
Requires-Dist: pyarrow==11.0.0; extra == "dev"
Requires-Dist: mypy==1.1.1; extra == "dev"
Requires-Dist: types-PyMySQL; extra == "dev"
Requires-Dist: types-PyYAML; extra == "dev"
Requires-Dist: types-Pygments; extra == "dev"
Requires-Dist: types-colorama; extra == "dev"
Requires-Dist: types-docutils; extra == "dev"
Requires-Dist: types-protobuf; extra == "dev"
Requires-Dist: types-psutil; extra == "dev"
Requires-Dist: types-python-dateutil; extra == "dev"
Requires-Dist: types-pytz; extra == "dev"
Requires-Dist: types-redis; extra == "dev"
Requires-Dist: types-requests; extra == "dev"
Requires-Dist: types-setuptools; extra == "dev"
Requires-Dist: types-tabulate; extra == "dev"
Requires-Dist: types-tqdm; extra == "dev"
Requires-Dist: types-typed-ast; extra == "dev"
Requires-Dist: types-urllib3; extra == "dev"
Requires-Dist: flake8==6.0.0; python_version >= "3.8" and extra == "dev"
Requires-Dist: pylint==2.15.0; python_version >= "3.8" and extra == "dev"
Requires-Dist: Sphinx<6.2.0,>=6.1.3; python_version >= "3.8" and extra == "dev"
Requires-Dist: docutils<0.19; python_version >= "3.8" and extra == "dev"
Requires-Dist: furo==2023.5.20; python_version >= "3.8" and extra == "dev"
Requires-Dist: sphinx-rtd-theme>=1.1; python_version >= "3.8" and extra == "dev"
Requires-Dist: myst-parser<1.1.0,>=1.0; python_version >= "3.8" and extra == "dev"
Requires-Dist: sphinx-copybutton==0.5.0; python_version >= "3.8" and extra == "dev"
Requires-Dist: sphinx-autobuild==2021.3.14; python_version >= "3.8" and extra == "dev"
Requires-Dist: sphinx-autodoc-typehints<1.23,>=1.22; python_version >= "3.8" and extra == "dev"
Requires-Dist: sphinx-design; python_version >= "3.8" and extra == "dev"
Requires-Dist: langchain==0.0.335; python_version >= "3.8" and extra == "dev"
Requires-Dist: tiktoken; python_version >= "3.8" and extra == "dev"
Provides-Extra: llm
Requires-Dist: datarobot-mlops>=10.0; extra == "llm"
Requires-Dist: datarobot>=3.5.0; extra == "llm"
Requires-Dist: langchain<0.1.17; extra == "llm"
Requires-Dist: langchain-community; extra == "llm"
Requires-Dist: openai; extra == "llm"
Requires-Dist: pydantic<3.0.0; extra == "llm"
Requires-Dist: tiktoken; extra == "llm"
Requires-Dist: torch; extra == "llm"
Provides-Extra: mlflow
Requires-Dist: mlflow; extra == "mlflow"
Provides-Extra: openblueprints
Requires-Dist: black; extra == "openblueprints"
Requires-Dist: category-encoders; extra == "openblueprints"
Requires-Dist: xgboost; extra == "openblueprints"
Requires-Dist: lightgbm; extra == "openblueprints"
Requires-Dist: vecstack; extra == "openblueprints"
Requires-Dist: scikit-learn; extra == "openblueprints"
Requires-Dist: gplearn; extra == "openblueprints"
Provides-Extra: spark
Requires-Dist: pyspark; extra == "spark"
